simple_query/__init__.py
simple_query/query.py
tests/__init__.py
tests/test_query.py
simple_query-0.0.2.dist-info/LICENSE
simple_query-0.0.2.dist-info/METADATA
simple_query-0.0.2.dist-info/WHEEL
simple_query-0.0.2.dist-info/top_level.txt
simple_query-0.0.2.dist-info/RECORD
