Metadata-Version: 2.1
Name: simple-query
Version: 0.0.2
Summary: Query pattern of containers of objects
Home-page: https://github.com/matannoam/SimpleQuery
Author: Matan Noam Shavit
License: UNKNOWN
Platform: UNKNOWN
Classifier: Programming Language :: Python :: 3
Classifier: License :: OSI Approved :: MIT License
Classifier: Operating System :: OS Independent
